<?xml version="1.0" encoding="UTF-8"?>
<con:soapui-project id="d0440f5a-ce33-4a9e-a4e2-0c9caa16bbab" activeEnvironment="Default" name="REST Project 7" resourceRoot="" soapui-version="5.2.1" abortOnError="false" runType="SEQUENTIAL" xmlns:con="http://eviware.com/soapui/config"><con:settings/><con:interface xsi:type="con:RestService" id="5d05ff05-cfb2-4fdc-b9b8-2affda8597af" wadlVersion="http://wadl.dev.java.net/2009/02" name="http://localhost:8080" type="rest" xmlns:xsi="http://www.w3.org/2001/XMLSchema-instance"><con:settings/><con:definitionCache/><con:endpoints><con:endpoint>http://localhost:8080</con:endpoint></con:endpoints><con:resource name="List" path="/spring-web-sample/rest/students/list" id="22b05412-9782-4dae-9fcb-dad3f8adfc31"><con:settings/><con:parameters/><con:method name="List with Accept JSON" id="dd4d13b0-199b-439a-90ce-5cac989918c2" method="GET"><con:settings/><con:parameters/><con:representation type="RESPONSE"><con:mediaType>application/xml;charset=UTF-8</con:mediaType><con:status>200</con:status><con:params/><con:element>List</con:element></con:representation><con:representation type="RESPONSE"><con:mediaType>application/json;charset=UTF-8</con:mediaType><con:status>200</con:status><con:params/><con:element>Response</con:element></con:representation><con:representation type="FAULT"><con:mediaType>text/html;charset=utf-8</con:mediaType><con:status>406</con:status><con:params/><con:element>html</con:element></con:representation><con:request name="Request 1" id="725781d8-a7f2-4556-9957-b5e8d0ea85d4" mediaType="application/json"><con:settings><con:setting id="com.eviware.soapui.impl.wsdl.WsdlRequest@request-headers">&lt;entry key="Accept" value="application/json" xmlns="http://eviware.com/soapui/config"/></con:setting></con:settings><con:endpoint>http://localhost:8080</con:endpoint><con:request/><con:originalUri>http://localhost/spring-web-sample/rest/students/list</con:originalUri><con:credentials><con:authType>No Authorization</con:authType></con:credentials><con:jmsConfig JMSDeliveryMode="PERSISTENT"/><con:jmsPropertyConfig/><con:parameters/></con:request></con:method></con:resource><con:resource name="Create with ContentType json" path="/spring-web-sample/rest/students/create" id="22b05412-9782-4dae-9fcb-dad3f8adfc31"><con:settings/><con:parameters/><con:method name="Create with Accept JSON" id="dd4d13b0-199b-439a-90ce-5cac989918c2" method="POST"><con:settings/><con:parameters/><con:representation type="RESPONSE"><con:mediaType>application/xml;charset=UTF-8</con:mediaType><con:status>200</con:status><con:params/><con:element>List</con:element></con:representation><con:representation type="RESPONSE"><con:mediaType>application/json;charset=UTF-8</con:mediaType><con:status>200</con:status><con:params/><con:element>Response</con:element></con:representation><con:representation type="FAULT"><con:mediaType>text/html;charset=utf-8</con:mediaType><con:status>405 406</con:status><con:params/><con:element>html</con:element></con:representation><con:representation type="REQUEST"><con:mediaType>application/json</con:mediaType><con:params/></con:representation><con:request name="Request 1" id="725781d8-a7f2-4556-9957-b5e8d0ea85d4" mediaType="application/json" postQueryString="false"><con:settings><con:setting id="com.eviware.soapui.impl.wsdl.WsdlRequest@request-headers">&lt;entry key="Accept" value="application/xml" xmlns="http://eviware.com/soapui/config"/></con:setting></con:settings><con:endpoint>http://localhost:8080</con:endpoint><con:request> {
      "id": 1,
      "name": "Sergey",
      "surname": "Kichenko",
      "group":       {
         "id": 1,
         "name": "Java developers"
 	}
 }</con:request><con:originalUri>http://localhost/spring-web-sample/rest/students/list</con:originalUri><con:credentials><con:authType>No Authorization</con:authType></con:credentials><con:jmsConfig JMSDeliveryMode="PERSISTENT"/><con:jmsPropertyConfig/><con:parameters/></con:request></con:method></con:resource></con:interface><con:properties/><con:wssContainer/><con:oAuth2ProfileContainer/><con:sensitiveInformation/></con:soapui-project>